Workbook

Sheet Assumptions
A1: PenSol — Excel Reference Model
A2: markiV Actuarial Engineering · Illustrative defined benefit pension valuation benchmark
A4: Assumption | B4: Value | C4: Units / basis | D4: Source / note
A5: Valuation date | B5: 2026-03-31 | C5: date | D5: Illustrative demo basis
A6: Discount rate | B6: 0.065 | C6: % p.a. | D6: Illustrative demo basis
A7: Salary growth | B7: 0.055 | C7: % p.a. | D7: Illustrative demo basis
A8: Pension increase | B8: 0.035 | C8: % p.a. | D8: Illustrative demo basis
A9: Deferred pension increase | B9: 0.04 | C9: % p.a. | D9: Illustrative demo basis
A10: Normal retirement age | B10: 60 | C10: years | D10: Illustrative scheme rule
A11: Accrual rate | B11: 0.016666667 | C11: pension per year of service | D11: 1/60th final-salary design
A12: Maximum pensionable service | B12: 40 | C12: years | D12: Illustrative scheme rule
A13: Spouse probability | B13: 0.75 | C13: % | D13: Illustrative simplification
A14: Spouse pension percentage | B14: 0.5 | C14: % of member pension | D14: Illustrative simplification
A15: Spouse annuity ratio | B15: 0.85 | C15: ratio | D15: Illustrative simplification
A16: Mortality scale | B16: 1 | C16: multiplier | D16: 1.00 = base illustrative mortality curve
A17: Scheme assets | B17: 6392400000 | C17: reporting currency units | D17: Illustrative market value
A18: Reporting currency | B18: INR | C18: display | D18: No FX conversion; data assumed in selected currency
A21: Important: This workbook is an independent reference implementation for the markiV PenSol demonstration. The member data are synthetic and the mortality basis is illustrative; this is not a prescribed IAS 19, ASC 715, funding or regulatory valuation.

Sheet Members
A1: Member ID | B1: Status | C1: Age | D1: Service (years) | E1: Pensionable salary (currency) | F1: Current pension (currency)
A2: A0215 | B2: Active | C2: 53 | D2: 2.7 | E2: 1852000 | F2: 0
A3: P0250 | B3: Pensioner | C3: 75 | D3: 20.3 | E3: 0 | F3: 434000
A4: P0219 | B4: Pensioner | C4: 67 | D4: 25.7 | E4: 0 | F4: 275000
A5: A0121 | B5: Active | C5: 24 | D5: 1.1 | E5: 344000 | F5: 0
A6: P0224 | B6: Pensioner | C6: 72 | D6: 26 | E6: 0 | F6: 297000
A7: P0222 | B7: Pensioner | C7: 66 | D7: 23 | E7: 0 | F7: 389000
A8: A0112 | B8: Active | C8: 42 | D8: 1.8 | E8: 1172000 | F8: 0
A9: P0072 | B9: Pensioner | C9: 79 | D9: 20.5 | E9: 0 | F9: 690000
A10: A0439 | B10: Active | C10: 50 | D10: 12.9 | E10: 1059000 | F10: 0
A11: A0270 | B11: Active | C11: 37 | D11: 2.3 | E11: 740000 | F11: 0
A12: D0125 | B12: Deferred | C12: 35 | D12: 3.2 | E12: 595000 | F12: 0
A13: P0133 | B13: Pensioner | C13: 76 | D13: 38.7 | E13: 0 | F13: 423000
... A1001: D0036 | B1001: Deferred | C1001: 57 | D1001: 20.3 | E1001: 1492000 | F1001: 0

Sheet Mortality
A1: Age | B1: Base qx | C1: Scaled qx | D1: px | E1: Increasing annuity factor | F1: l(x) from age 18
A2: 18 | B2: 0.00024213897 | C2: =MIN(0.45,MAX(0.00005,B2*Assumptions!$B$16)) -> 0.00024213897 | D2: =1-C2 -> 0.99975786 | E2: =D2/(1+Assumptions!$B$6)*(1+(1+Assumptions!$B$8)*E3) -> 28.167948 | F2: 1
A3: 19 | B3: 0.0002448842 | C3: =MIN(0.45,MAX(0.00005,B3*Assumptions!$B$16)) -> 0.0002448842 | D3: =1-C3 -> 0.99975512 | E3: =D3/(1+Assumptions!$B$6)*(1+(1+Assumptions!$B$8)*E4) -> 28.025246 | F3: =F2*D2 -> 0.99975786
A4: 20 | B4: 0.00024796984 | C4: =MIN(0.45,MAX(0.00005,B4*Assumptions!$B$16)) -> 0.00024796984 | D4: =1-C4 -> 0.99975203 | E4: =D4/(1+Assumptions!$B$6)*(1+(1+Assumptions!$B$8)*E5) -> 27.878452 | F4: =F3*D3 -> 0.99951304
A5: 21 | B5: 0.0002514381 | C5: =MIN(0.45,MAX(0.00005,B5*Assumptions!$B$16)) -> 0.0002514381 | D5: =1-C5 -> 0.99974856 | E5: =D5/(1+Assumptions!$B$6)*(1+(1+Assumptions!$B$8)*E6) -> 27.727455 | F5: =F4*D4 -> 0.99926519
A6: 22 | B6: 0.00025533643 | C6: =MIN(0.45,MAX(0.00005,B6*Assumptions!$B$16)) -> 0.00025533643 | D6: =1-C6 -> 0.99974466 | E6: =D6/(1+Assumptions!$B$6)*(1+(1+Assumptions!$B$8)*E7) -> 27.572141 | F6: =F5*D5 -> 0.99901393
A7: 23 | B7: 0.00025971814 | C7: =MIN(0.45,MAX(0.00005,B7*Assumptions!$B$16)) -> 0.00025971814 | D7: =1-C7 -> 0.99974028 | E7: =D7/(1+Assumptions!$B$6)*(1+(1+Assumptions!$B$8)*E8) -> 27.412396 | F7: =F6*D6 -> 0.99875885
A8: 24 | B8: 0.00026464319 | C8: =MIN(0.45,MAX(0.00005,B8*Assumptions!$B$16)) -> 0.00026464319 | D8: =1-C8 -> 0.99973536 | E8: =D8/(1+Assumptions!$B$6)*(1+(1+Assumptions!$B$8)*E9) -> 27.248103 | F8: =F7*D7 -> 0.99849945
A9: 25 | B9: 0.00027017895 | C9: =MIN(0.45,MAX(0.00005,B9*Assumptions!$B$16)) -> 0.00027017895 | D9: =1-C9 -> 0.99972982 | E9: =D9/(1+Assumptions!$B$6)*(1+(1+Assumptions!$B$8)*E10) -> 27.079141 | F9: =F8*D8 -> 0.99823521
A10: 26 | B10: 0.00027640114 | C10: =MIN(0.45,MAX(0.00005,B10*Assumptions!$B$16)) -> 0.00027640114 | D10: =1-C10 -> 0.9997236 | E10: =D10/(1+Assumptions!$B$6)*(1+(1+Assumptions!$B$8)*E11) -> 26.905391 | F10: =F9*D9 -> 0.99796551
A11: 27 | B11: 0.00028339488 | C11: =MIN(0.45,MAX(0.00005,B11*Assumptions!$B$16)) -> 0.00028339488 | D11: =1-C11 -> 0.99971661 | E11: =D11/(1+Assumptions!$B$6)*(1+(1+Assumptions!$B$8)*E12) -> 26.726728 | F11: =F10*D10 -> 0.99768967
A12: 28 | B12: 0.00029125584 | C12: =MIN(0.45,MAX(0.00005,B12*Assumptions!$B$16)) -> 0.00029125584 | D12: =1-C12 -> 0.99970874 | E12: =D12/(1+Assumptions!$B$6)*(1+(1+Assumptions!$B$8)*E13) -> 26.543028 | F12: =F11*D11 -> 0.99740693
A13: 29 | B13: 0.00030009157 | C13: =MIN(0.45,MAX(0.00005,B13*Assumptions!$B$16)) -> 0.00030009157 | D13: =1-C13 -> 0.99969991 | E13: =D13/(1+Assumptions!$B$6)*(1+(1+Assumptions!$B$8)*E14) -> 26.354165 | F13: =F12*D12 -> 0.99711643
A14: 30 | B14: 0.00031002292 | C14: =MIN(0.45,MAX(0.00005,B14*Assumptions!$B$16)) -> 0.00031002292 | D14: =1-C14 -> 0.99968998 | E14: =D14/(1+Assumptions!$B$6)*(1+(1+Assumptions!$B$8)*E15) -> 26.16001 | F14: =F13*D13 -> 0.9968172
... A103: 119 | B103: 0.45 | C103: =MIN(0.45,MAX(0.00005,B103*Assumptions!$B$16)) -> 0.45 | D103: =1-C103 -> 0.55 | E103: =D103/(1+Assumptions!$B$6)*(1+(1+Assumptions!$B$8)*E104) -> 0.79246843 | F103: =F102*D102 -> 1.0440639e-06
A104: 120 | B104: 0.45 | C104: =MIN(0.45,MAX(0.00005,B104*Assumptions!$B$16)) -> 0.45 | D104: =1-C104 -> 0.55 | E104: =D104/(1+Assumptions!$B$6) -> 0.51643192 | F104: =F103*D103 -> 5.7423513e-07

Sheet Valuation
A1: Member ID | B1: Status | C1: Age | D1: Service | E1: Pensionable salary | F1: Current pension | G1: Years to retirement | H1: Projected salary | I1: Projected service | J1: Annual pension at retirement | K1: Survival to retirement | L1: Annuity factor | M1: Spouse loading | N1: Discount factor | O1: PV liability
A2: =Members!A2 -> A0215 | B2: =Members!B2 -> Active | C2: =Members!C2 -> 53 | D2: =Members!D2 -> 2.7 | E2: =Members!E2 -> 1852000 | F2: =Members!F2 -> 0 | G2: =MAX(0,Assumptions!$B$10-C2) -> 7 | H2: =IF(B2="Active",E2*(1+Assumptions!$B$7)^G2,E2) -> 2694065.8 | I2: =IF(B2="Active",MIN(Assumptions!$B$12,D2+G2),IF(B2="Deferred",MIN(Assumptions!$B$12,D2),D2)) -> 9.7 | J2: =IF(B2="Active",H2*I2*Assumptions!$B$11,IF(B2="Deferred",E2*I2*Assumptions!$B$11*(1+Assumptions!$B$9)^G2,F2)) -> 435540.64 | K2: =IF(B2="Pensioner",1,VLOOKUP(Assumptions!$B$10,Mortality!$A$2:$F$104,6,FALSE)/VLOOKUP(C2,Mortality!$A$2:$F$104,6,FALSE)) -> 0.98503 | L2: =VLOOKUP(IF(B2="Pensioner",C2,Assumptions!$B$10),Mortality!$A$2:$E$104,5,FALSE) -> 17.29679 | M2: =1+Assumptions!$B$13*Assumptions!$B$14*Assumptions!$B$15 -> 1.31875 | N2: =IF(B2="Pensioner",1,1/(1+Assumptions!$B$6)^G2) -> 0.64350621 | O2: =J2*K2*L2*M2*N2 -> 6297365.1
A3: =Members!A3 -> P0250 | B3: =Members!B3 -> Pensioner | C3: =Members!C3 -> 75 | D3: =Members!D3 -> 20.3 | E3: =Members!E3 -> 0 | F3: =Members!F3 -> 434000 | G3: =MAX(0,Assumptions!$B$10-C3) -> 0 | H3: =IF(B3="Active",E3*(1+Assumptions!$B$7)^G3,E3) -> 0 | I3: =IF(B3="Active",MIN(Assumptions!$B$12,D3+G3),IF(B3="Deferred",MIN(Assumptions!$B$12,D3),D3)) -> 20.3 | J3: =IF(B3="Active",H3*I3*Assumptions!$B$11,IF(B3="Deferred",E3*I3*Assumptions!$B$11*(1+Assumptions!$B$9)^G3,F3)) -> 434000 | K3: =IF(B3="Pensioner",1,VLOOKUP(Assumptions!$B$10,Mortality!$A$2:$F$104,6,FALSE)/VLOOKUP(C3,Mortality!$A$2:$F$104,6,FALSE)) -> 1 | L3: =VLOOKUP(IF(B3="Pensioner",C3,Assumptions!$B$10),Mortality!$A$2:$E$104,5,FALSE) -> 10.662475 | M3: =1+Assumptions!$B$13*Assumptions!$B$14*Assumptions!$B$15 -> 1.31875 | N3: =IF(B3="Pensioner",1,1/(1+Assumptions!$B$6)^G3) -> 1 | O3: =J3*K3*L3*M3*N3 -> 6102534.2
A4: =Members!A4 -> P0219 | B4: =Members!B4 -> Pensioner | C4: =Members!C4 -> 67 | D4: =Members!D4 -> 25.7 | E4: =Members!E4 -> 0 | F4: =Members!F4 -> 275000 | G4: =MAX(0,Assumptions!$B$10-C4) -> 0 | H4: =IF(B4="Active",E4*(1+Assumptions!$B$7)^G4,E4) -> 0 | I4: =IF(B4="Active",MIN(Assumptions!$B$12,D4+G4),IF(B4="Deferred",MIN(Assumptions!$B$12,D4),D4)) -> 25.7 | J4: =IF(B4="Active",H4*I4*Assumptions!$B$11,IF(B4="Deferred",E4*I4*Assumptions!$B$11*(1+Assumptions!$B$9)^G4,F4)) -> 275000 | K4: =IF(B4="Pensioner",1,VLOOKUP(Assumptions!$B$10,Mortality!$A$2:$F$104,6,FALSE)/VLOOKUP(C4,Mortality!$A$2:$F$104,6,FALSE)) -> 1 | L4: =VLOOKUP(IF(B4="Pensioner",C4,Assumptions!$B$10),Mortality!$A$2:$E$104,5,FALSE) -> 14.31648 | M4: =1+Assumptions!$B$13*Assumptions!$B$14*Assumptions!$B$15 -> 1.31875 | N4: =IF(B4="Pensioner",1,1/(1+Assumptions!$B$6)^G4) -> 1 | O4: =J4*K4*L4*M4*N4 -> 5191961.1
A5: =Members!A5 -> A0121 | B5: =Members!B5 -> Active | C5: =Members!C5 -> 24 | D5: =Members!D5 -> 1.1 | E5: =Members!E5 -> 344000 | F5: =Members!F5 -> 0 | G5: =MAX(0,Assumptions!$B$10-C5) -> 36 | H5: =IF(B5="Active",E5*(1+Assumptions!$B$7)^G5,E5) -> 2363997.4 | I5: =IF(B5="Active",MIN(Assumptions!$B$12,D5+G5),IF(B5="Deferred",MIN(Assumptions!$B$12,D5),D5)) -> 37.1 | J5: =IF(B5="Active",H5*I5*Assumptions!$B$11,IF(B5="Deferred",E5*I5*Assumptions!$B$11*(1+Assumptions!$B$9)^G5,F5)) -> 1461738.4 | K5: =IF(B5="Pensioner",1,VLOOKUP(Assumptions!$B$10,Mortality!$A$2:$F$104,6,FALSE)/VLOOKUP(C5,Mortality!$A$2:$F$104,6,FALSE)) -> 0.96871087 | L5: =VLOOKUP(IF(B5="Pensioner",C5,Assumptions!$B$10),Mortality!$A$2:$E$104,5,FALSE) -> 17.29679 | M5: =1+Assumptions!$B$13*Assumptions!$B$14*Assumptions!$B$15 -> 1.31875 | N5: =IF(B5="Pensioner",1,1/(1+Assumptions!$B$6)^G5) -> 0.10361297 | O5: =J5*K5*L5*M5*N5 -> 3346616.3
A6: =Members!A6 -> P0224 | B6: =Members!B6 -> Pensioner | C6: =Members!C6 -> 72 | D6: =Members!D6 -> 26 | E6: =Members!E6 -> 0 | F6: =Members!F6 -> 297000 | G6: =MAX(0,Assumptions!$B$10-C6) -> 0 | H6: =IF(B6="Active",E6*(1+Assumptions!$B$7)^G6,E6) -> 0 | I6: =IF(B6="Active",MIN(Assumptions!$B$12,D6+G6),IF(B6="Deferred",MIN(Assumptions!$B$12,D6),D6)) -> 26 | J6: =IF(B6="Active",H6*I6*Assumptions!$B$11,IF(B6="Deferred",E6*I6*Assumptions!$B$11*(1+Assumptions!$B$9)^G6,F6)) -> 297000 | K6: =IF(B6="Pensioner",1,VLOOKUP(Assumptions!$B$10,Mortality!$A$2:$F$104,6,FALSE)/VLOOKUP(C6,Mortality!$A$2:$F$104,6,FALSE)) -> 1 | L6: =VLOOKUP(IF(B6="Pensioner",C6,Assumptions!$B$10),Mortality!$A$2:$E$104,5,FALSE) -> 12.047202 | M6: =1+Assumptions!$B$13*Assumptions!$B$14*Assumptions!$B$15 -> 1.31875 | N6: =IF(B6="Pensioner",1,1/(1+Assumptions!$B$6)^G6) -> 1 | O6: =J6*K6*L6*M6*N6 -> 4718512.7
A7: =Members!A7 -> P0222 | B7: =Members!B7 -> Pensioner | C7: =Members!C7 -> 66 | D7: =Members!D7 -> 23 | E7: =Members!E7 -> 0 | F7: =Members!F7 -> 389000 | G7: =MAX(0,Assumptions!$B$10-C7) -> 0 | H7: =IF(B7="Active",E7*(1+Assumptions!$B$7)^G7,E7) -> 0 | I7: =IF(B7="Active",MIN(Assumptions!$B$12,D7+G7),IF(B7="Deferred",MIN(Assumptions!$B$12,D7),D7)) -> 23 | J7: =IF(B7="Active",H7*I7*Assumptions!$B$11,IF(B7="Deferred",E7*I7*Assumptions!$B$11*(1+Assumptions!$B$9)^G7,F7)) -> 389000 | K7: =IF(B7="Pensioner",1,VLOOKUP(Assumptions!$B$10,Mortality!$A$2:$F$104,6,FALSE)/VLOOKUP(C7,Mortality!$A$2:$F$104,6,FALSE)) -> 1 | L7: =VLOOKUP(IF(B7="Pensioner",C7,Assumptions!$B$10),Mortality!$A$2:$E$104,5,FALSE) -> 14.759005 | M7: =1+Assumptions!$B$13*Assumptions!$B$14*Assumptions!$B$15 -> 1.31875 | N7: =IF(B7="Pensioner",1,1/(1+Assumptions!$B$6)^G7) -> 1 | O7: =J7*K7*L7*M7*N7 -> 7571277.4
A8: =Members!A8 -> A0112 | B8: =Members!B8 -> Active | C8: =Members!C8 -> 42 | D8: =Members!D8 -> 1.8 | E8: =Members!E8 -> 1172000 | F8: =Members!F8 -> 0 | G8: =MAX(0,Assumptions!$B$10-C8) -> 18 | H8: =IF(B8="Active",E8*(1+Assumptions!$B$7)^G8,E8) -> 3072358.5 | I8: =IF(B8="Active",MIN(Assumptions!$B$12,D8+G8),IF(B8="Deferred",MIN(Assumptions!$B$12,D8),D8)) -> 19.8 | J8: =IF(B8="Active",H8*I8*Assumptions!$B$11,IF(B8="Deferred",E8*I8*Assumptions!$B$11*(1+Assumptions!$B$9)^G8,F8)) -> 1013878.3 | K8: =IF(B8="Pensioner",1,VLOOKUP(Assumptions!$B$10,Mortality!$A$2:$F$104,6,FALSE)/VLOOKUP(C8,Mortality!$A$2:$F$104,6,FALSE)) -> 0.97507997 | L8: =VLOOKUP(IF(B8="Pensioner",C8,Assumptions!$B$10),Mortality!$A$2:$E$104,5,FALSE) -> 17.29679 | M8: =1+Assumptions!$B$13*Assumptions!$B$14*Assumptions!$B$15 -> 1.31875 | N8: =IF(B8="Pensioner",1,1/(1+Assumptions!$B$6)^G8) -> 0.32188969 | O8: =J8*K8*L8*M8*N8 -> 7258737.8
A9: =Members!A9 -> P0072 | B9: =Members!B9 -> Pensioner | C9: =Members!C9 -> 79 | D9: =Members!D9 -> 20.5 | E9: =Members!E9 -> 0 | F9: =Members!F9 -> 690000 | G9: =MAX(0,Assumptions!$B$10-C9) -> 0 | H9: =IF(B9="Active",E9*(1+Assumptions!$B$7)^G9,E9) -> 0 | I9: =IF(B9="Active",MIN(Assumptions!$B$12,D9+G9),IF(B9="Deferred",MIN(Assumptions!$B$12,D9),D9)) -> 20.5 | J9: =IF(B9="Active",H9*I9*Assumptions!$B$11,IF(B9="Deferred",E9*I9*Assumptions!$B$11*(1+Assumptions!$B$9)^G9,F9)) -> 690000 | K9: =IF(B9="Pensioner",1,VLOOKUP(Assumptions!$B$10,Mortality!$A$2:$F$104,6,FALSE)/VLOOKUP(C9,Mortality!$A$2:$F$104,6,FALSE)) -> 1 | L9: =VLOOKUP(IF(B9="Pensioner",C9,Assumptions!$B$10),Mortality!$A$2:$E$104,5,FALSE) -> 8.8309326 | M9: =1+Assumptions!$B$13*Assumptions!$B$14*Assumptions!$B$15 -> 1.31875 | N9: =IF(B9="Pensioner",1,1/(1+Assumptions!$B$6)^G9) -> 1 | O9: =J9*K9*L9*M9*N9 -> 8035596.7
A10: =Members!A10 -> A0439 | B10: =Members!B10 -> Active | C10: =Members!C10 -> 50 | D10: =Members!D10 -> 12.9 | E10: =Members!E10 -> 1059000 | F10: =Members!F10 -> 0 | G10: =MAX(0,Assumptions!$B$10-C10) -> 10 | H10: =IF(B10="Active",E10*(1+Assumptions!$B$7)^G10,E10) -> 1808925 | I10: =IF(B10="Active",MIN(Assumptions!$B$12,D10+G10),IF(B10="Deferred",MIN(Assumptions!$B$12,D10),D10)) -> 22.9 | J10: =IF(B10="Active",H10*I10*Assumptions!$B$11,IF(B10="Deferred",E10*I10*Assumptions!$B$11*(1+Assumptions!$B$9)^G10,F10)) -> 690406.37 | K10: =IF(B10="Pensioner",1,VLOOKUP(Assumptions!$B$10,Mortality!$A$2:$F$104,6,FALSE)/VLOOKUP(C10,Mortality!$A$2:$F$104,6,FALSE)) -> 0.98127299 | L10: =VLOOKUP(IF(B10="Pensioner",C10,Assumptions!$B$10),Mortality!$A$2:$E$104,5,FALSE) -> 17.29679 | M10: =1+Assumptions!$B$13*Assumptions!$B$14*Assumptions!$B$15 -> 1.31875 | N10: =IF(B10="Pensioner",1,1/(1+Assumptions!$B$6)^G10) -> 0.53272604 | O10: =J10*K10*L10*M10*N10 -> 8232401.5
A11: =Members!A11 -> A0270 | B11: =Members!B11 -> Active | C11: =Members!C11 -> 37 | D11: =Members!D11 -> 2.3 | E11: =Members!E11 -> 740000 | F11: =Members!F11 -> 0 | G11: =MAX(0,Assumptions!$B$10-C11) -> 23 | H11: =IF(B11="Active",E11*(1+Assumptions!$B$7)^G11,E11) -> 2535352.2 | I11: =IF(B11="Active",MIN(Assumptions!$B$12,D11+G11),IF(B11="Deferred",MIN(Assumptions!$B$12,D11),D11)) -> 25.3 | J11: =IF(B11="Active",H11*I11*Assumptions!$B$11,IF(B11="Deferred",E11*I11*Assumptions!$B$11*(1+Assumptions!$B$9)^G11,F11)) -> 1069073.5 | K11: =IF(B11="Pensioner",1,VLOOKUP(Assumptions!$B$10,Mortality!$A$2:$F$104,6,FALSE)/VLOOKUP(C11,Mortality!$A$2:$F$104,6,FALSE)) -> 0.97273561 | L11: =VLOOKUP(IF(B11="Pensioner",C11,Assumptions!$B$10),Mortality!$A$2:$E$104,5,FALSE) -> 17.29679 | M11: =1+Assumptions!$B$13*Assumptions!$B$14*Assumptions!$B$15 -> 1.31875 | N11: =IF(B11="Pensioner",1,1/(1+Assumptions!$B$6)^G11) -> 0.23494111 | O11: =J11*K11*L11*M11*N11 -> 5573004.4
A12: =Members!A12 -> D0125 | B12: =Members!B12 -> Deferred | C12: =Members!C12 -> 35 | D12: =Members!D12 -> 3.2 | E12: =Members!E12 -> 595000 | F12: =Members!F12 -> 0 | G12: =MAX(0,Assumptions!$B$10-C12) -> 25 | H12: =IF(B12="Active",E12*(1+Assumptions!$B$7)^G12,E12) -> 595000 | I12: =IF(B12="Active",MIN(Assumptions!$B$12,D12+G12),IF(B12="Deferred",MIN(Assumptions!$B$12,D12),D12)) -> 3.2 | J12: =IF(B12="Active",H12*I12*Assumptions!$B$11,IF(B12="Deferred",E12*I12*Assumptions!$B$11*(1+Assumptions!$B$9)^G12,F12)) -> 84595.873 | K12: =IF(B12="Pensioner",1,VLOOKUP(Assumptions!$B$10,Mortality!$A$2:$F$104,6,FALSE)/VLOOKUP(C12,Mortality!$A$2:$F$104,6,FALSE)) -> 0.97197408 | L12: =VLOOKUP(IF(B12="Pensioner",C12,Assumptions!$B$10),Mortality!$A$2:$E$104,5,FALSE) -> 17.29679 | M12: =1+Assumptions!$B$13*Assumptions!$B$14*Assumptions!$B$15 -> 1.31875 | N12: =IF(B12="Pensioner",1,1/(1+Assumptions!$B$6)^G12) -> 0.20713801 | O12: =J12*K12*L12*M12*N12 -> 388500.56
A13: =Members!A13 -> P0133 | B13: =Members!B13 -> Pensioner | C13: =Members!C13 -> 76 | D13: =Members!D13 -> 38.7 | E13: =Members!E13 -> 0 | F13: =Members!F13 -> 423000 | G13: =MAX(0,Assumptions!$B$10-C13) -> 0 | H13: =IF(B13="Active",E13*(1+Assumptions!$B$7)^G13,E13) -> 0 | I13: =IF(B13="Active",MIN(Assumptions!$B$12,D13+G13),IF(B13="Deferred",MIN(Assumptions!$B$12,D13),D13)) -> 38.7 | J13: =IF(B13="Active",H13*I13*Assumptions!$B$11,IF(B13="Deferred",E13*I13*Assumptions!$B$11*(1+Assumptions!$B$9)^G13,F13)) -> 423000 | K13: =IF(B13="Pensioner",1,VLOOKUP(Assumptions!$B$10,Mortality!$A$2:$F$104,6,FALSE)/VLOOKUP(C13,Mortality!$A$2:$F$104,6,FALSE)) -> 1 | L13: =VLOOKUP(IF(B13="Pensioner",C13,Assumptions!$B$10),Mortality!$A$2:$E$104,5,FALSE) -> 10.201356 | M13: =1+Assumptions!$B$13*Assumptions!$B$14*Assumptions!$B$15 -> 1.31875 | N13: =IF(B13="Pensioner",1,1/(1+Assumptions!$B$6)^G13) -> 1 | O13: =J13*K13*L13*M13*N13 -> 5690635.2
... A1001: =Members!A1001 -> D0036 | B1001: =Members!B1001 -> Deferred | C1001: =Members!C1001 -> 57 | D1001: =Members!D1001 -> 20.3 | E1001: =Members!E1001 -> 1492000 | F1001: =Members!F1001 -> 0 | G1001: =MAX(0,Assumptions!$B$10-C1001) -> 3 | H1001: =IF(B1001="Active",E1001*(1+Assumptions!$B$7)^G1001,E1001) -> 1492000 | I1001: =IF(B1001="Active",MIN(Assumptions!$B$12,D1001+G1001),IF(B1001="Deferred",MIN(Assumptions!$B$12,D1001),D1001)) -> 20.3 | J1001: =IF(B1001="Active",H1001*I1001*Assumptions!$B$11,IF(B1001="Deferred",E1001*I1001*Assumptions!$B$11*(1+Assumptions!$B$9)^G1001,F1001)) -> 567823.85 | K1001: =IF(B1001="Pensioner",1,VLOOKUP(Assumptions!$B$10,Mortality!$A$2:$F$104,6,FALSE)/VLOOKUP(C1001,Mortality!$A$2:$F$104,6,FALSE)) -> 0.99220039 | L1001: =VLOOKUP(IF(B1001="Pensioner",C1001,Assumptions!$B$10),Mortality!$A$2:$E$104,5,FALSE) -> 17.29679 | M1001: =1+Assumptions!$B$13*Assumptions!$B$14*Assumptions!$B$15 -> 1.31875 | N1001: =IF(B1001="Pensioner",1,1/(1+Assumptions!$B$6)^G1001) -> 0.82784909 | O1001: =J1001*K1001*L1001*M1001*N1001 -> 10638789

Sheet Summary
A1: PenSol — Scheme Summary
A3: Metric | B3: Value
A4: Total members | B4: =COUNTA(Members!A2:A1001) -> 1000
A5: DB liability | B5: =SUM(Valuation!O2:O1001) -> 6.9482992e+09
A6: Scheme assets | B6: =Assumptions!B17 -> 6392400000
A7: Funding ratio | B7: =B6/B5 -> 0.91999492
A8: Surplus / (deficit) | B8: =B6-B5 -> -5.5589922e+08
A9: Data basis | B9: Synthetic demo census
A11: Status | B11: PV liability
A12: Active | B12: =SUMIF(Valuation!B2:B1001,"Active",Valuation!O2:O1001) -> 5.2624711e+09
A13: Deferred | B13: =SUMIF(Valuation!B2:B1001,"Deferred",Valuation!O2:O1001) -> 3.7295233e+08
A14: Pensioner | B14: =SUMIF(Valuation!B2:B1001,"Pensioner",Valuation!O2:O1001) -> 1.3128758e+09
A15: Total | B15: =SUM(B12:B14) -> 6.9482992e+09

Sheet Validation
A1: Excel ↔ JavaScript Frozen Benchmark
G2: Validation principle: freeze a base assumption set, independently calculate benchmark liabilities in Excel, then reconcile the reusable JavaScript engine at both aggregate and member level. Changing assumptions should trigger a new benchmark, not an artificial 'failure'.
A3: Check | B3: Value
A4: Reference total liability | B4: 6.9482992e+09
A5: Excel calculated total | B5: =SUM(Valuation!O2:O1001) -> 6.9482992e+09
A6: Difference | B6: =B5-B4 -> 9.5367432e-06
A7: Tolerance | B7: 0.01
A10: Member ID | B10: Reference liability | C10: Excel liability | D10: Difference | E10: Status
A11: A0001 | B11: 6554434.5 | C11: =VLOOKUP(A11,Valuation!$A$2:$O$1001,15,FALSE) -> 6554434.5 | D11: =C11-B11 -> -9.406358e-08 | E11: =IF(ABS(D11)<=$B$7,"Matched","Review") -> Matched
A12: A0002 | B12: 13579308 | C12: =VLOOKUP(A12,Valuation!$A$2:$O$1001,15,FALSE) -> 13579308 | D12: =C12-B12 -> 1.1920929e-07 | E12: =IF(ABS(D12)<=$B$7,"Matched","Review") -> Matched
A13: A0003 | B13: 9534806.1 | C13: =VLOOKUP(A13,Valuation!$A$2:$O$1001,15,FALSE) -> 9534806.1 | D13: =C13-B13 -> -1.2852252e-07 | E13: =IF(ABS(D13)<=$B$7,"Matched","Review") -> Matched
A14: A0004 | B14: 10810693 | C14: =VLOOKUP(A14,Valuation!$A$2:$O$1001,15,FALSE) -> 10810693 | D14: =C14-B14 -> -1.1734664e-07 | E14: =IF(ABS(D14)<=$B$7,"Matched","Review") -> Matched
A15: D0001 | B15: 2534793.5 | C15: =VLOOKUP(A15,Valuation!$A$2:$O$1001,15,FALSE) -> 2534793.5 | D15: =C15-B15 -> 1.8998981e-07 | E15: =IF(ABS(D15)<=$B$7,"Matched","Review") -> Matched
A16: D0002 | B16: 668259.37 | C16: =VLOOKUP(A16,Valuation!$A$2:$O$1001,15,FALSE) -> 668259.37 | D16: =C16-B16 -> -8.7078661e-08 | E16: =IF(ABS(D16)<=$B$7,"Matched","Review") -> Matched
A17: D0003 | B17: 13580124 | C17: =VLOOKUP(A17,Valuation!$A$2:$O$1001,15,FALSE) -> 13580124 | D17: =C17-B17 -> -2.1979213e-07 | E17: =IF(ABS(D17)<=$B$7,"Matched","Review") -> Matched
A18: D0004 | B18: 1992513.8 | C18: =VLOOKUP(A18,Valuation!$A$2:$O$1001,15,FALSE) -> 1992513.8 | D18: =C18-B18 -> -2.0023435e-07 | E18: =IF(ABS(D18)<=$B$7,"Matched","Review") -> Matched
A19: P0001 | B19: 5475386.5 | C19: =VLOOKUP(A19,Valuation!$A$2:$O$1001,15,FALSE) -> 5475386.5 | D19: =C19-B19 -> -3.4458935e-07 | E19: =IF(ABS(D19)<=$B$7,"Matched","Review") -> Matched
A20: P0002 | B20: 5983150.2 | C20: =VLOOKUP(A20,Valuation!$A$2:$O$1001,15,FALSE) -> 5983150.2 | D20: =C20-B20 -> 4.1350722e-07 | E20: =IF(ABS(D20)<=$B$7,"Matched","Review") -> Matched
A21: P0003 | B21: 7029364.2 | C21: =VLOOKUP(A21,Valuation!$A$2:$O$1001,15,FALSE) -> 7029364.2 | D21: =C21-B21 -> -7.5437129e-08 | E21: =IF(ABS(D21)<=$B$7,"Matched","Review") -> Matched
A22: P0004 | B22: 3149813.1 | C22: =VLOOKUP(A22,Valuation!$A$2:$O$1001,15,FALSE) -> 3149813.1 | D22: =C22-B22 -> -2.8312206e-07 | E22: =IF(ABS(D22)<=$B$7,"Matched","Review") -> Matched
